{
    "hard": {
        "fail": {
            "risk": 0,
            "message": "",
            "looseRequiredItem": true,
            "fine": {
                "min": 0,
                "max": 0
            }
        },
        "success": {
            "message": "",
            "sellItems": false,
            "amount": {
                "min": 1,
                "max": 5
            },
            "loot": [
                "goldfish",
                "blobfish",
                "cod",
                "salmon",
                "tuna",
                "sardine",
                "catfish",
                "jellyfish",
                "sea_turtle",
                "starfish",
                "octopus",
                "crab",
                "lobster",
                "squid",
                "shark"
            ]
        }
    },
    "easy": {
        "fail": {
            "risk": 0,
            "message": "",
            "looseRequiredItem": true,
            "fine": {
                "min": 0,
                "max": 0
            }
        },
        "success": {
            "message": "",
            "sellItems": false,
            "amount": {
                "min": 1,
                "max": 5
            },
            "loot": [
                "goldfish",
                "cod",
                "salmon",
                "tuna",
                "sardine",
                "catfish",
                "jellyfish",
                "crab",
                "starfish"
            ]
        }
    }
}