{
    "coinz_plus": {
        "name": "Coinz Plus",
        "price": {
            "monthly": 200,
            "quarterly": 500
        },
        "logo": "https://cdn.coinzbot.xyz/logo.png",
        "perks": [
            "All 5s cooldowns reduced to 1s",
            "Able to buy up to 12 farming plots",
            "Unlock /weekly",
            "Unlock an exclusive Coinz Plus badge",
            "Gamble limit increased to 🪙 10.000",
            "Earn up to 🪙 300/day with /daily (Free tier: 🪙 150/day)",
            "Change your profile color",
            "Get faster ticket support"
        ]
    },
    "coinz_pro": {
        "name": "Coinz Pro",
        "price": {
            "monthly": 500,
            "quarterly": 1200
        },
        "logo": "https://cdn.coinzbot.xyz/logo.png",
        "perks": [
            "All perks from Coinz Plus",
            "Able to buy up to 15 farming plots",
            "Unlock /monthly",
            "Unlock an exclusive Coinz Pro badge",
            "Gamble limit increased to 🪙 20.000",
            "Get 2 lucky wheel spins for every vote",
            "Get a lucky wheel spin with /daily",
            "Earn double XP",
            "Gamble cooldowns reduced from 10 to 4 minutes",
            "Hire a 6th employee for your business",
            "Donate someone up to 🪙 25.000 using /pay"
        ]
    }
}
